cloudwatcher/__init__.py
cloudwatcher/__main__.py
cloudwatcher/argparser.py
cloudwatcher/cli.py
cloudwatcher/cloudwatcher.py
cloudwatcher/const.py
cloudwatcher/logwatcher.py
cloudwatcher/metric_handlers.py
cloudwatcher/metricwatcher.py
cloudwatcher/preset.py
cloudwatcher/presets/nephele_cpu_usage_user.json
cloudwatcher/presets/nephele_disk_used_percent.json
cloudwatcher/presets/nephele_disk_used_percent_nephele_data.json
cloudwatcher/presets/nephele_mem.json
cloudwatcher/presets/nephele_mem_cached.json
cloudwatcher/presets/nephele_processes_dead.json
cloudwatcher/presets/nephele_swap_used.json
cloudwatcher/presets/nephele_swap_used_percent.json
cloudwatcher-0.2.0.dist-info/entry_points.txt
cloudwatcher-0.2.0.dist-info/LICENSE
cloudwatcher-0.2.0.dist-info/WHEEL
cloudwatcher-0.2.0.dist-info/METADATA
cloudwatcher-0.2.0.dist-info/RECORD
