Metadata-Version: 2.1
Name: cloudwatcher
Version: 0.2.0
Summary: A tool for monitoring AWS CloudWatch metrics
Author: Michal Stolarczyk
Author-email: stolarczyk.michal93@gmail.com
Requires-Python: >=3.7,<4.0
Classifier: Programming Language :: Python :: 3
Classifier: Programming Language :: Python :: 3.10
Classifier: Programming Language :: Python :: 3.7
Classifier: Programming Language :: Python :: 3.8
Classifier: Programming Language :: Python :: 3.9
Requires-Dist: boto3 (>=1.26.62,<1.27.0)
Requires-Dist: matplotlib (>=3.5.1,<3.6.0)
Requires-Dist: pydantic (>=1.10.2,<1.11.0)
Requires-Dist: pytz (>=2022.1,<2022.2)
Requires-Dist: rich (>=12.2.0,<12.3.0)
